{"display_speak_rate": "1", "addons": {"example.py": {"active": false, "verify": false}, "example_with_variable.py": {"active": false, "verify": false}}, "wifi_password": "", "gmail_password": "tzO2f/yZ8oXyguEC8IMbpA==", "enable_log_cloud": "true", "ifttt_key": "", "enable_log_file": "true", "telegram_bot_token": "2142323225:AAE3MwisK8-T2RQ7Pls_CJE58HuVzd_oKzE", "autoconnect_wifi": "true", "clouddata_key": "", "display_speak_voice": "US English Female", "wifi_ssid": "", "gmail_username": "", "display_speak_pitch": "1", "pushbullet_token": ""}